promptrek/__init__.py
promptrek/__main__.py
promptrek/adapters/__init__.py
promptrek/adapters/amazon_q.py
promptrek/adapters/base.py
promptrek/adapters/claude.py
promptrek/adapters/cline.py
promptrek/adapters/continue_adapter.py
promptrek/adapters/copilot.py
promptrek/adapters/cursor.py
promptrek/adapters/jetbrains.py
promptrek/adapters/kiro.py
promptrek/adapters/mcp_mixin.py
promptrek/adapters/registry.py
promptrek/adapters/sync_mixin.py
promptrek/adapters/tabnine.py
promptrek/adapters/windsurf.py
promptrek/cli/__init__.py
promptrek/cli/main.py
promptrek/cli/yaml_writer.py
promptrek/cli/commands/__init__.py
promptrek/cli/commands/agents.py
promptrek/cli/commands/config_ignores.py
promptrek/cli/commands/generate.py
promptrek/cli/commands/hooks.py
promptrek/cli/commands/init.py
promptrek/cli/commands/migrate.py
promptrek/cli/commands/plugins.py
promptrek/cli/commands/preview.py
promptrek/cli/commands/sync.py
promptrek/cli/commands/validate.py
promptrek/core/__init__.py
promptrek/core/exceptions.py
promptrek/core/models.py
promptrek/core/parser.py
promptrek/core/validator.py
promptrek/utils/__init__.py
promptrek/utils/conditionals.py
promptrek/utils/gitignore.py
promptrek/utils/imports.py
promptrek/utils/variables.py
promptrek-0.3.1.dist-info/licenses/LICENSE
promptrek-0.3.1.dist-info/METADATA
promptrek-0.3.1.dist-info/WHEEL
promptrek-0.3.1.dist-info/entry_points.txt
promptrek-0.3.1.dist-info/top_level.txt
promptrek-0.3.1.dist-info/RECORD
