Metadata-Version: 2.4
Name: promptrek
Version: 0.3.1
Summary: Universal AI Editor prompt storage solution
Author-email: Addie Rudy <developer@flamingquaks.dev>
Project-URL: Homepage, https://github.com/flamingquaks/promptrek
Project-URL: Repository, https://github.com/flamingquaks/promptrek
Project-URL: Documentation, https://github.com/flamingquaks/promptrek/tree/main/docs
Project-URL: Issues, https://github.com/flamingquaks/promptrek/issues
Keywords: ai,prompts,copilot,cursor,continue,cli,editor,tool,utility
Classifier: Intended Audience :: Developers
Classifier: Operating System :: OS Independent
Classifier: Programming Language :: Python :: 3
Classifier: Programming Language :: Python :: 3.9
Classifier: Programming Language :: Python :: 3.10
Classifier: Programming Language :: Python :: 3.11
Classifier: Programming Language :: Python :: 3.12
Classifier: Topic :: Software Development
Classifier: Topic :: Utilities
Requires-Python: >=3.9
License-File: LICENSE
Requires-Dist: click>=8.0.0
Requires-Dist: PyYAML>=5.4
Requires-Dist: Jinja2>=3.1.0
Requires-Dist: pydantic>=2.0.0
Provides-Extra: dev
Requires-Dist: pytest>=7.0.0; extra == "dev"
Requires-Dist: pytest-cov>=4.0.0; extra == "dev"
Requires-Dist: black>=22.0.0; extra == "dev"
Requires-Dist: flake8>=5.0.0; extra == "dev"
Requires-Dist: mypy>=1.0.0; extra == "dev"
Requires-Dist: isort>=5.0.0; extra == "dev"
Requires-Dist: types-pyyaml>=6.0.12.20241230; extra == "dev"
Requires-Dist: pre-commit>=3.0.0; extra == "dev"
Requires-Dist: yamllint>=1.35.0; extra == "dev"
Dynamic: license-file
